MANIFEST.in
README.rst
config-template.yaml
setup.py
metzoo_opc/__init__.py
metzoo_opc/data.py
metzoo_opc/db.py
metzoo_opc/opc.py
metzoo_opc/run.py
metzoo_opc_sdk.egg-info/PKG-INFO
metzoo_opc_sdk.egg-info/SOURCES.txt
metzoo_opc_sdk.egg-info/dependency_links.txt
metzoo_opc_sdk.egg-info/not-zip-safe
metzoo_opc_sdk.egg-info/requires.txt
metzoo_opc_sdk.egg-info/top_level.txt