Metadata-Version: 1.1
Name: metzoo-opc-sdk
Version: 0.2.7
Summary: OPC SDK for Metzoo
Home-page: https://bitbucket.org/edrans/metzoo-opc-sdk
Author: Edrans
Author-email: info@edrans.com
License: MIT
Keywords: metzoo monitoring metric opc
Platform: UNKNOWN
Classifier: Development Status :: 3 - Alpha
Classifier: License :: OSI Approved :: MIT License
Classifier: Programming Language :: Python :: 2.7
